c1algo1/ParsePreferencesDocument.py
c1algo1/__init__.py
c1algo1/assign_from_historical_offering.py
c1algo1/assign_time_slots.py
c1algo1/bounding.py
c1algo1/course.py
c1algo1/format_schedule.py
c1algo1/generate_course_list.py
c1algo1/modify_input_json.py
c1algo1/node_data.py
c1algo1/prof_pref_randomizer.py
c1algo1/professors_to_courses_branch_and_bound.py
c1algo1/program_planer_parse.py
c1algo1/scheduler.py
c1algo1/scheduler_tools.py
c1algo1/test_professors_to_courses_branch_and_bound.py
c1algo1/test_tools.py
c1algo1/time_slots.py
c1algo1/use_modify_input_json.py
c1algo1/validator.py
c1algo1-3.0.2.dist-info/LICENSE.TXT
c1algo1-3.0.2.dist-info/METADATA
c1algo1-3.0.2.dist-info/WHEEL
c1algo1-3.0.2.dist-info/top_level.txt
c1algo1-3.0.2.dist-info/RECORD
